bits/__init__.py
bits/backupify/__init__.py
bits_backupify-1.0.2.dist-info/METADATA
bits_backupify-1.0.2.dist-info/WHEEL
bits_backupify-1.0.2.dist-info/top_level.txt
bits_backupify-1.0.2.dist-info/RECORD
