Metadata-Version: 2.1
Name: bits-backupify
Version: 1.0.2
Summary: BITS Backupify
Home-page: UNKNOWN
Author: Lukas Karlsson
Author-email: karlsson@broadinstitute.org
License: Apache Software License
Platform: UNKNOWN
